needlr/__init__.py
needlr/_http.py
needlr/client.py
needlr/admin/domain.py
needlr/admin/label.py
needlr/admin/item/__init__.py
needlr/admin/item/item.py
needlr/admin/item/types.py
needlr/admin/tenant/__init__.py
needlr/admin/tenant/tenant.py
needlr/admin/workspace/__init__.py
needlr/admin/workspace/adminworkspace.py
needlr/auth/__init__.py
needlr/auth/auth.py
needlr/auth/scopes.py
needlr/core/__init__.py
needlr/core/capacity/__init__.py
needlr/core/capacity/capacity.py
needlr/core/gateway/gateway.py
needlr/core/git/git.py
needlr/core/item/__init__.py
needlr/core/item/item.py
needlr/core/jobscheduler/jobscheduler.py
needlr/core/workspace/__init__.py
needlr/core/workspace/identity.py
needlr/core/workspace/role.py
needlr/core/workspace/workspace.py
needlr/dataactivator/__init__.py
needlr/dataactivator/reflex/__init__.py
needlr/dataactivator/reflex/reflex.py
needlr/dataengineering/__init__.py
needlr/dataengineering/lakehouse.py
needlr/dataengineering/notebook.py
needlr/dataengineering/sqlendpoints.py
needlr/datafactory/__init__.py
needlr/datafactory/datapipeline.py
needlr/datascience/__init__.py
needlr/datascience/mlexperiment.py
needlr/datascience/mlmodel.py
needlr/datawarehouse/__init__.py
needlr/datawarehouse/mirroredwarehouse.py
needlr/datawarehouse/warehouse.py
needlr/industrysolutions/__init__.py
needlr/models/__init__.py
needlr/models/adminworkspace.py
needlr/models/capacity.py
needlr/models/dashboard.py
needlr/models/datamart.py
needlr/models/datapipeline.py
needlr/models/domain.py
needlr/models/eventhouse.py
needlr/models/eventstream.py
needlr/models/gateway.py
needlr/models/git.py
needlr/models/item.py
needlr/models/jobscheduler.py
needlr/models/kqldashboard.py
needlr/models/kqldatabase.py
needlr/models/kqlqueryset.py
needlr/models/lakehouse.py
needlr/models/mlexperiment.py
needlr/models/mlmodel.py
needlr/models/notebook.py
needlr/models/paginatedreport.py
needlr/models/reflex.py
needlr/models/report.py
needlr/models/semanticmodel.py
needlr-0.2.1.dist-info/licenses/LICENSE
needlr-0.2.1.dist-info/METADATA
needlr-0.2.1.dist-info/WHEEL
needlr-0.2.1.dist-info/top_level.txt
needlr-0.2.1.dist-info/RECORD
