Metadata-Version: 2.4
Name: needlr
Version: 0.2.1
Summary: Needlr provides a unified cross-experience Microsoft Fabric SDK.
Author-email: Tonio Lora <tonio.lora@microsoft.com>, Tim Brown <timothy.brown@microsoft.com>, Emily Nguyen <emily.nguyen@microsoft.com>, Bret Myers <bret.myers@microsoft.com>, Will Johnson <will.johnson@microsoft.com>
Classifier: Development Status :: 4 - Beta
Classifier: Intended Audience :: Developers
Classifier: Intended Audience :: Information Technology
Classifier: Intended Audience :: System Administrators
Classifier: Topic :: Software Development
Classifier: License :: OSI Approved :: MIT License
Classifier: Programming Language :: Python
Classifier: Programming Language :: Python :: 3
Classifier: Programming Language :: Python :: 3.8
Classifier: Programming Language :: Python :: 3.9
Classifier: Programming Language :: Python :: 3.10
Classifier: Programming Language :: Python :: 3.11
Classifier: Programming Language :: Python :: 3.12
Requires-Python: >=3.8
License-File: LICENSE
Requires-Dist: msal>=1.31.0
Requires-Dist: pydantic>=2.8.0
Requires-Dist: pyodbc>=5.2.0
Requires-Dist: requests>=2.32.3
Provides-Extra: dev
Requires-Dist: annotated-types==0.7.0; extra == "dev"
Requires-Dist: azure-identity>=1.19.0; extra == "dev"
Requires-Dist: azure-storage-file-datalake>=12.18.0; extra == "dev"
Requires-Dist: pytest>=8.3.4; extra == "dev"
Requires-Dist: pytest-order==1.2.1; extra == "dev"
Requires-Dist: python-dotenv==1.0.1; extra == "dev"
Requires-Dist: ruff==0.7.1; extra == "dev"
Requires-Dist: sphinx>=7.1.2; extra == "dev"
Dynamic: license-file
